hbtools/__init__.py
hbtools/logger.py
hbtools/misc.py
hbtools/py.typed
hbtools/show_img.py
hbtools-0.4.3.dist-info/METADATA
hbtools-0.4.3.dist-info/WHEEL
hbtools-0.4.3.dist-info/licenses/LICENSE
hbtools-0.4.3.dist-info/RECORD
