Metadata-Version: 2.3
Name: hbtools
Version: 0.4.3
Summary: Package containing a few python utils functions.
Project-URL: Homepage, https://github.com/hoel-bagard/hbtools
Project-URL: Bug Tracker, https://github.com/hoel-bagard/hbtools/issues
Author: Bagard Hoel
License: MIT
License-File: LICENSE
Classifier: Intended Audience :: Developers
Classifier: License :: OSI Approved :: MIT License
Classifier: Operating System :: OS Independent
Classifier: Programming Language :: Python :: 3
Classifier: Programming Language :: Python :: 3.10
Classifier: Programming Language :: Python :: 3.11
Requires-Python: >=3.10
Requires-Dist: numpy>=1.21
Requires-Dist: typing-extensions; python_version < '3.11'
Provides-Extra: build
Requires-Dist: hatch; extra == 'build'
Provides-Extra: dev
Requires-Dist: opencv-stubs; extra == 'dev'
Requires-Dist: pip-tools; extra == 'dev'
Requires-Dist: pre-commit; extra == 'dev'
Requires-Dist: pyright; extra == 'dev'
Requires-Dist: ruff; extra == 'dev'
Requires-Dist: term-image; extra == 'dev'
Provides-Extra: flake8
Requires-Dist: flake8; extra == 'flake8'
Requires-Dist: flake8-broken-line; extra == 'flake8'
Requires-Dist: flake8-bugbear; extra == 'flake8'
Requires-Dist: flake8-builtins; extra == 'flake8'
Requires-Dist: flake8-commas; extra == 'flake8'
Requires-Dist: flake8-comprehensions; extra == 'flake8'
Requires-Dist: flake8-docstrings; extra == 'flake8'
Requires-Dist: flake8-import-order; extra == 'flake8'
Requires-Dist: flake8-noqa; extra == 'flake8'
Requires-Dist: flake8-pyproject; extra == 'flake8'
Requires-Dist: flake8-quotes; extra == 'flake8'
Requires-Dist: pep8-naming; extra == 'flake8'
Provides-Extra: opencv
Requires-Dist: opencv-python>=4.7; extra == 'opencv'
Provides-Extra: opencv-headless
Requires-Dist: opencv-python-headless>=4.7; extra == 'opencv-headless'
Provides-Extra: terminal
Requires-Dist: pillow; extra == 'terminal'
Requires-Dist: term-image; extra == 'terminal'
Provides-Extra: test
Requires-Dist: nox; extra == 'test'
Requires-Dist: pytest; extra == 'test'
